oqspy/__init__.py
oqspy/cli.py
oqspy/oqspy.py
oqspy-0.1.3.dist-info/AUTHORS.rst
oqspy-0.1.3.dist-info/LICENSE
oqspy-0.1.3.dist-info/METADATA
oqspy-0.1.3.dist-info/WHEEL
oqspy-0.1.3.dist-info/entry_points.txt
oqspy-0.1.3.dist-info/top_level.txt
oqspy-0.1.3.dist-info/RECORD
