Metadata-Version: 2.1
Name: oqspy
Version: 0.1.3
Summary: Open Quantum Systems Modelling Package
Home-page: https://github.com/GillianGrayson/oqspy
Author: Igor Yusipov
Author-email: yusipov.igor@gmail.com
License: MIT license
Keywords: oqspy
Platform: UNKNOWN
Classifier: Development Status :: 2 - Pre-Alpha
Classifier: Intended Audience :: Developers
Classifier: License :: OSI Approved :: MIT License
Classifier: Natural Language :: English
Classifier: Programming Language :: Python :: 3
Classifier: Programming Language :: Python :: 3.5
Classifier: Programming Language :: Python :: 3.6
Classifier: Programming Language :: Python :: 3.7
Classifier: Programming Language :: Python :: 3.8
Requires-Python: >=3.5
Requires-Dist: Click (>=7.0)
